ramp_frontend/__init__.py
ramp_frontend/_version.py
ramp_frontend/cli.py
ramp_frontend/forms.py
ramp_frontend/testing.py
ramp_frontend/utils.py
ramp_frontend/wsgi.py
ramp_frontend/static/css/style.css
ramp_frontend/static/css/themes/flat-blue.css
ramp_frontend/static/img/Alex.jpg
ramp_frontend/static/img/Mehdi.png
ramp_frontend/static/img/hands.jpg
ramp_frontend/static/img/logo_CDS.svg
ramp_frontend/static/img/logo_CDS_black.svg
ramp_frontend/static/img/logo_CDS_footer.svg
ramp_frontend/static/img/missing_face.png
ramp_frontend/static/img/ramp.jpg
ramp_frontend/static/img/ramp_room.jpg
ramp_frontend/static/img/ysitruk.png
ramp_frontend/static/img/backdrop/micro_carbon.png
ramp_frontend/static/img/backdrop/tactile_noise.png
ramp_frontend/static/img/partners/cnrs.png
ramp_frontend/static/img/partners/mines.png
ramp_frontend/static/img/partners/polytechnique.jpg
ramp_frontend/static/img/partners/telecom.png
ramp_frontend/static/img/partners/upsaclay.png
ramp_frontend/static/img/partners/upsud.jpg
ramp_frontend/static/js/alert.js
ramp_frontend/static/js/app.js
ramp_frontend/static/js/button.js
ramp_frontend/static/js/card.js
ramp_frontend/static/js/index.js
ramp_frontend/static/js/list.js
ramp_frontend/static/js/modal.js
ramp_frontend/static/js/theming.js
ramp_frontend/static/lib/css/animate.min.css
ramp_frontend/static/lib/css/bootstrap-switch.min.css
ramp_frontend/static/lib/css/bootstrap.min.css
ramp_frontend/static/lib/css/bootstrap.min.css.map
ramp_frontend/static/lib/css/checkbox3.min.css
ramp_frontend/static/lib/css/dataTables.bootstrap.css
ramp_frontend/static/lib/css/font-awesome.min.css
ramp_frontend/static/lib/css/jquery.dataTables.min.css
ramp_frontend/static/lib/css/select2.min.css
ramp_frontend/static/lib/fonts/FontAwesome.otf
ramp_frontend/static/lib/fonts/fontawesome-webfont.eot
ramp_frontend/static/lib/fonts/fontawesome-webfont.svg
ramp_frontend/static/lib/fonts/fontawesome-webfont.ttf
ramp_frontend/static/lib/fonts/fontawesome-webfont.woff
ramp_frontend-0.10.1.dist-info/LICENSE
ramp_frontend-0.10.1.dist-info/METADATA
ramp_frontend-0.10.1.dist-info/WHEEL
ramp_frontend-0.10.1.dist-info/entry_points.txt
ramp_frontend-0.10.1.dist-info/top_level.txt
ramp_frontend-0.10.1.dist-info/RECORD
