Metadata-Version: 2.1
Name: ramp-frontend
Version: 0.10.1
Summary: Website for RAMP
Home-page: https://github.com/paris-saclay-cds/ramp-board
Maintainer: A. Boucaud, B. Kegl, G. Lemaitre, J. Van den Bossche
Maintainer-email: boucaud.alexandre@gmail.com, guillaume.lemaitre@inria.fr
License: BSD (3-clause)
Download-URL: https://github.com/paris-saclay-cds/ramp-board
Platform: UNKNOWN
Classifier: Intended Audience :: Science/Research
Classifier: Intended Audience :: Developers
Classifier: License :: OSI Approved
Classifier: Programming Language :: Python
Classifier: Topic :: Software Development
Classifier: Topic :: Scientific/Engineering
Classifier: Operating System :: Microsoft :: Windows
Classifier: Operating System :: POSIX
Classifier: Operating System :: Unix
Classifier: Operating System :: MacOS
Classifier: Programming Language :: Python :: 3.6
Classifier: Programming Language :: Python :: 3.7
Classifier: Programming Language :: Python :: 3.8
Requires-Python: >=3.7
Requires-Dist: bokeh
Requires-Dist: click
Requires-Dist: Flask
Requires-Dist: Flask-Login
Requires-Dist: Flask-Mail
Requires-Dist: Flask-SQLAlchemy
Requires-Dist: Flask-WTF
Requires-Dist: itsdangerous
Requires-Dist: numpy
Requires-Dist: pandas
Provides-Extra: docs
Requires-Dist: sphinx ; extra == 'docs'
Requires-Dist: sphinx-rtd-theme ; extra == 'docs'
Requires-Dist: numpydoc ; extra == 'docs'
Provides-Extra: tests
Requires-Dist: pytest ; extra == 'tests'
Requires-Dist: pytest-cov ; extra == 'tests'
